webtest/__init__.py
webtest/app.py
webtest/compat.py
webtest/debugapp.py
webtest/ext.py
webtest/forms.py
webtest/http.py
webtest/lint.py
webtest/response.py
webtest/sel.py
webtest/utils.py
WebTest-3.0.5.dist-info/METADATA
WebTest-3.0.5.dist-info/WHEEL
WebTest-3.0.5.dist-info/entry_points.txt
WebTest-3.0.5.dist-info/top_level.txt
WebTest-3.0.5.dist-info/RECORD
